bc_django_modeltranslator-0.0.4.dist-info/licenses/LICENSE
bc_modeltranslator/__init__.py
bc_modeltranslator/apps.py
bc_modeltranslator/dataclasses.py
bc_modeltranslator/decorators.py
bc_modeltranslator/manager.py
bc_modeltranslator/models.py
bc_modeltranslator/queryset.py
bc_modeltranslator/registry.py
bc_modeltranslator/settings.py
bc_modeltranslator/util_model.py
bc_django_modeltranslator-0.0.4.dist-info/METADATA
bc_django_modeltranslator-0.0.4.dist-info/WHEEL
bc_django_modeltranslator-0.0.4.dist-info/top_level.txt
bc_django_modeltranslator-0.0.4.dist-info/RECORD
